vibefunc/__init__.py
vibefunc-0.1.0.dist-info/METADATA
vibefunc-0.1.0.dist-info/WHEEL
vibefunc-0.1.0.dist-info/top_level.txt
vibefunc-0.1.0.dist-info/RECORD
