Metadata-Version: 2.4
Name: vibefunc
Version: 0.1.0
Summary: Vibe your Python functions just for fun
Author-email: Wenjie Wei <weiwenjie@westlake.edu.cn>
License: MIT
Project-URL: homepage, https://github.com/wjwei-handsome/vibefunc
Requires-Python: >=3.10
Requires-Dist: httpx[socks]>=0.28.1
Requires-Dist: openai>=1.99.6
